remote_mcp_cli/__init__.py
remote_mcp_cli/__main__.py
remote_mcp_cli/config.py
remote_mcp_cli/stdio.py
remote_mcp_cli-0.8.0.dist-info/METADATA
remote_mcp_cli-0.8.0.dist-info/WHEEL
remote_mcp_cli-0.8.0.dist-info/entry_points.txt
remote_mcp_cli-0.8.0.dist-info/top_level.txt
remote_mcp_cli-0.8.0.dist-info/RECORD
