Metadata-Version: 2.4
Name: remote-mcp-cli
Version: 0.8.0
Summary: Minimal MCP client CLI
Requires-Python: >=3.8
Requires-Dist: click
Requires-Dist: httpx
